pymultibot/__init__.py
pymultibot/__version__.py
pymultibot/multibot.py
pymultibot-1.0.0.dist-info/METADATA
pymultibot-1.0.0.dist-info/WHEEL
pymultibot-1.0.0.dist-info/top_level.txt
pymultibot-1.0.0.dist-info/RECORD
